fastnode/__init__.py
fastnode/_about.py
fastnode/_cli.py
fastnode/core.py
fastnode/export.py
fastnode/api/__init__.py
fastnode/api/readyapi_app.py
fastnode/api/readyapi_utils.py
fastnode/components/__init__.py
fastnode/components/outputs.py
fastnode/components/types.py
fastnode/tasks/__init__.py
fastnode/ui/__init__.py
fastnode/ui/schema_utils.py
fastnode/ui/streamlit_ui.py
fastnode/ui/streamlit_utils.py
fastnode/utils/__init__.py
fastnode-0.0.10.dist-info/LICENSE
fastnode-0.0.10.dist-info/METADATA
fastnode-0.0.10.dist-info/WHEEL
fastnode-0.0.10.dist-info/entry_points.txt
fastnode-0.0.10.dist-info/top_level.txt
fastnode-0.0.10.dist-info/RECORD
